{
	"info": {
		"_postman_id": "eba530c4-9361-46e0-85fe-8b9cbdd3def5",
		"name": "pro-cloud 获取token",
		"schema": "https://schema.getpostman.com/json/collection/v2.1.0/collection.json"
	},
	"item": [
		{
			"name": "获取token",
			"request": {
				"method": "POST",
				"header": [
					{
						"key": "Authorization",
						"value": "Basic Y2xpZW50OnNlY3JldA=="
					}
				],
				"body": {
					"mode": "urlencoded",
					"urlencoded": [
						{
							"key": "grant_type",
							"value": "password",
							"type": "text"
						},
						{
							"key": "username",
							"value": "myadmin",
							"type": "text"
						},
						{
							"key": "password",
							"value": "123456",
							"type": "text"
						}
					]
				},
				"url": {
					"raw": "http://localhost:9999/auth/oauth/token",
					"protocol": "http",
					"host": [
						"localhost"
					],
					"port": "9999",
					"path": [
						"auth",
						"oauth",
						"token"
					]
				},
				"description": "获取token"
			},
			"response": []
		}
	],
	"protocolProfileBehavior": {}
}